pyproject.toml
yaicli/__init__.py
yaicli/chat.py
yaicli/cli.py
yaicli/cmd_handler.py
yaicli/completer.py
yaicli/config.py
yaicli/console.py
yaicli/const.py
yaicli/context.py
yaicli/entry.py
yaicli/exceptions.py
yaicli/history.py
yaicli/printer.py
yaicli/render.py
yaicli/role.py
yaicli/schemas.py
yaicli/utils.py
yaicli/functions/__init__.py
yaicli/functions/buildin/execute_shell_command.py
yaicli/functions/buildin/fetch_webpage.py
yaicli/functions/buildin/fs_edit_file.py
yaicli/functions/buildin/fs_file_operations.py
yaicli/functions/buildin/fs_get_filesystem_info.py
yaicli/functions/buildin/fs_list_directory.py
yaicli/functions/buildin/fs_read_file.py
yaicli/functions/buildin/fs_read_image.py
yaicli/functions/buildin/fs_search_files.py
yaicli/functions/buildin/fs_write_file.py
yaicli/functions/buildin/get_weather.py
yaicli/functions/buildin/web_search.py
yaicli/llms/__init__.py
yaicli/llms/client.py
yaicli/llms/provider.py
yaicli/llms/providers/__init__.py
yaicli/llms/providers/ai21_provider.py
yaicli/llms/providers/anthropic_provider.py
yaicli/llms/providers/bailian_provider.py
yaicli/llms/providers/cerebras_provider.py
yaicli/llms/providers/chatglm_provider.py
yaicli/llms/providers/chutes_provider.py
yaicli/llms/providers/cohere_provider.py
yaicli/llms/providers/deepseek_provider.py
yaicli/llms/providers/doubao_provider.py
yaicli/llms/providers/fireworks_provider.py
yaicli/llms/providers/gemini_provider.py
yaicli/llms/providers/groq_provider.py
yaicli/llms/providers/huggingface_provider.py
yaicli/llms/providers/infiniai_provider.py
yaicli/llms/providers/longcat_provider.py
yaicli/llms/providers/minimax_provider.py
yaicli/llms/providers/mistral_provider.py
yaicli/llms/providers/modelscope_provider.py
yaicli/llms/providers/moonshot_provider.py
yaicli/llms/providers/nvida_provider.py
yaicli/llms/providers/ollama_provider.py
yaicli/llms/providers/openai_compatible_provider.py
yaicli/llms/providers/openai_provider.py
yaicli/llms/providers/openrouter_provider.py
yaicli-0.11.1.dist-info/METADATA
yaicli-0.11.1.dist-info/WHEEL
yaicli-0.11.1.dist-info/entry_points.txt
yaicli-0.11.1.dist-info/licenses/LICENSE
yaicli-0.11.1.dist-info/RECORD
