Metadata-Version: 2.4
Name: yaicli
Version: 0.11.1
Summary: A simple CLI tool to interact with LLM
Project-URL: Homepage, https://github.com/belingud/yaicli
Project-URL: Repository, https://github.com/belingud/yaicli
Project-URL: Documentation, https://github.com/belingud/yaicli
Author-email: belingud <im.victor@qq.com>
License:                                  Apache License
License-File: LICENSE
Keywords: ai,ai-assistant,ai-chat,ai-interaction,anthropic,chatglm,chatgpt,claude,cli,cohere,command-line,completion,console-application,conversation,deepseek,gemini,gpt,groq,huggingface,inference,interactive,language-model,llm,llms,mistral,modelscope,nlp,ollama,openai,prompt,python-tool,sambanova,shell-integration,siliconflow,terminal,terminal-interface,text-generation,vertexai,xai
Classifier: License :: OSI Approved :: Apache Software License
Classifier: Operating System :: OS Independent
Classifier: Programming Language :: Python :: 3
Requires-Python: >=3.10
Requires-Dist: anthropic[bedrock,vertex]>=0.57.1
Requires-Dist: click>=8.1.8
Requires-Dist: ddgs>=9.6.1
Requires-Dist: distro>=1.9.0
Requires-Dist: fastmcp>=2.10.1
Requires-Dist: httpx>=0.28.1
Requires-Dist: instructor>=1.7.9
Requires-Dist: json-repair>=0.44.1
Requires-Dist: openai>=1.76.0
Requires-Dist: prompt-toolkit>=3.0.50
Requires-Dist: rich>=13.9.4
Requires-Dist: socksio>=1.0.0
Requires-Dist: trafilatura>=1.6.1
Requires-Dist: typer>=0.16.0
Provides-Extra: all
Requires-Dist: cerebras-cloud-sdk>=1.35.0; extra == 'all'
Requires-Dist: cohere>=5.15.0; extra == 'all'
Requires-Dist: fireworks-ai>=0.15.15; extra == 'all'
Requires-Dist: google-genai>=1.20.0; extra == 'all'
Requires-Dist: huggingface-hub>=0.33.0; extra == 'all'
Requires-Dist: mistralai>=1.8.2; extra == 'all'
Requires-Dist: ollama>=0.5.1; extra == 'all'
Requires-Dist: volcengine-python-sdk>=3.0.15; extra == 'all'
Provides-Extra: cerebras
Requires-Dist: cerebras-cloud-sdk>=1.35.0; extra == 'cerebras'
Provides-Extra: cohere
Requires-Dist: cohere>=5.15.0; extra == 'cohere'
Provides-Extra: doubao
Requires-Dist: volcengine-python-sdk>=3.0.15; extra == 'doubao'
Provides-Extra: fireworks
Requires-Dist: fireworks-ai>=0.15.15; extra == 'fireworks'
Provides-Extra: gemini
Requires-Dist: google-genai>=1.20.0; extra == 'gemini'
Provides-Extra: huggingface
Requires-Dist: huggingface-hub>=0.33.0; extra == 'huggingface'
Provides-Extra: mistral
Requires-Dist: mistralai>=1.8.2; extra == 'mistral'
Provides-Extra: ollama
Requires-Dist: ollama>=0.5.1; extra == 'ollama'
